<?xml version="1.0" encoding="utf-8"?>
<users>
<user id="1"><name>Mario</name><surname>Mariani</surname><username>mmariani</username><password>pppp</password><definition>artista</definition><email>mmariani@gmail.com</email><studies>Universita</studies><sex>M</sex><realm>uniurb</realm></user><user id="2"><name>radha</name><surname>giannotti</surname><username>radha</username><password>radha</password><definition>artista</definition><email>radha.giannotti@gmail.com</email><studies>nuove tecnologie</studies><sex>F</sex><realm>aba</realm></user><user id="3"><name>bib</name><surname>bob</surname><username>aba</username><password>io</password><definition>artista</definition><email>del@led</email><studies>internetto</studies><sex>M</sex><realm>isia</realm></user><user id="4"><name>Adriana</name><surname>De Luca</surname><username>ad</username><password>belloarmando</password><definition>artista</definition><email>no</email><studies>nemmeno</studies><sex>F</sex><realm>aba</realm></user><user id="5"><name>denis</name><surname>panattoni</surname><username>denis</username><password>no</password><definition>artista</definition><email/><studies/><sex>M</sex><realm>aba</realm></user><user id="6"><name> Lorenzo</name><surname>Lembo</surname><username>L'embolo</username><password>tortadimele</password><definition>artista</definition><email>lembovnskj@gmail.com</email><studies>nta</studies><sex>M</sex><realm>aba</realm></user><user id="7"><name>marika</name><surname>semeraro</surname><username>marika96</username><password>odioprofondo123</password><definition>artista</definition><email>marika_love_96@hotmail.it</email><studies>accademia</studies><sex>F</sex><realm>aba</realm></user><user id="8"><name>vladimir</name><surname>bertozzi</surname><username>vladimir</username><password>vladimir</password><definition>artista</definition><email>bertozzi12@hotmail</email><studies>nta</studies><sex>M</sex><realm>aba</realm></user><user id="9"><name>cristina</name><surname>palmisani</surname><username>cris</username><password>@Cristina08</password><definition>studente</definition><email>cristina.palmisani@outlook.it</email><studies>forse</studies><sex>F</sex><realm>uniurb</realm></user><user id="10"><name>diego</name><surname>santangeli</surname><username>tino</username><password>aladin</password><definition>artista</definition><email>santangeli.diego@gmail.com</email><studies>NTA2</studies><sex>M</sex><realm>aba</realm></user><user id="11"><name>raffaele</name><surname>carnevali</surname><username>scraffix</username><password>pippo</password><definition>artista</definition><email>raffi.carnevali@gmail.com</email><studies>studente</studies><sex>M</sex><realm>aba</realm></user><user id="12"><name>sara</name><surname>porfiri</surname><username>sara.porfiri</username><password>saretta</password><definition>studente</definition><email>si ce l'ho</email><studies>ogni tanto</studies><sex>F</sex><realm>aba</realm></user><user id="13"><name>Adeo</name><surname>Di Nicola</surname><username>adeodinicola</username><password>lol</password><definition>artista</definition><email>no</email><studies>forse</studies><sex>M</sex><realm>aba</realm></user><user id="14"><name>Alex David</name><surname>Luchetti</surname><username>alex.luchetti</username><password>alex.luchetti</password><definition>studente</definition><email>aldalu93@me.com</email><studies/><sex>M</sex><realm>aba</realm></user></users>
